MANIFEST.in
README.md
requirements.txt
setup.py
byteplus_rec_core/__init__.py
byteplus_rec_core/__version__.py
byteplus_rec_core/abstract_region.py
byteplus_rec_core/abtract_host_availabler.py
byteplus_rec_core/auth.py
byteplus_rec_core/constant.py
byteplus_rec_core/exception.py
byteplus_rec_core/host_availabler_factory.py
byteplus_rec_core/http_caller.py
byteplus_rec_core/http_client.py
byteplus_rec_core/option.py
byteplus_rec_core/options.py
byteplus_rec_core/ping_host_availabler.py
byteplus_rec_core/status_helper.py
byteplus_rec_core/utils.py
byteplus_rec_core.egg-info/PKG-INFO
byteplus_rec_core.egg-info/SOURCES.txt
byteplus_rec_core.egg-info/dependency_links.txt
byteplus_rec_core.egg-info/requires.txt
byteplus_rec_core.egg-info/top_level.txt
byteplus_rec_core/metrics/__init__.py
byteplus_rec_core/metrics/constant.py
byteplus_rec_core/metrics/metrics.py
byteplus_rec_core/metrics/metrics_collector.py
byteplus_rec_core/metrics/metrics_example.py
byteplus_rec_core/metrics/metrics_log.py
byteplus_rec_core/metrics/metrics_option.py
byteplus_rec_core/metrics/metrics_reporter.py
byteplus_rec_core/metrics/protocol/__init__.py
byteplus_rec_core/metrics/protocol/byteplus_rec_sdk_metrics_pb2.py